{
    "$schema": "https://json-schema.org/draft/2020-12/schema",
    "$id": "AgwfEntryInvalidNamespace.json",
    "type": "object",
    "properties": {
        "id": {
            "type": "string",
            "const": "AGWF004"
        },
        "severity": {
            "type": "string",
            "const": "error"
        },
        "summary": {
            "type": "string",
            "const": "Invalid namespace"
        },
        "remediation": {
            "type": "string",
            "const": "Workflow '{0}' must be declared in a namespace. Global namespace is not supported."
        },
        "since": {
            "type": "string",
            "const": "0.2.0"
        }
    },
    "required": [
        "id",
        "severity",
        "summary",
        "remediation",
        "since"
    ],
    "description": "AGWF004 — Invalid namespace."
}